{
  "EmulationProfile": "NamcoMkdxUsa",
  "EmulatorType": "TeknoParrot",
  "ExecutableName": "MK_AGP3_FINAL.exe",
  "ExtraParameters": "",
  "GameNameInternal": "",
  "GamePath": "",
  "GameProfileRevision": 19,
  "GasAxisMax": 255,
  "HasTpoSupport": true,
  "OnlineProfileURL": "",
  "TestMenuExtraParameters": "",
  "TestMenuParameter": "",
  "xAxisMax": 255,
  "yAxisMax": 255,
  "ConfigValues": [
    {
      "CategoryName": "General",
      "FieldName": "Input API",
      "FieldOptions": [
        "DirectInput",
        "XInput"
      ],
      "FieldType": "Dropdown",
      "FieldValue": "DirectInput"
    },
    {
      "CategoryName": "General",
      "FieldName": "Windowed",
      "FieldOptions": [],
      "FieldType": "Bool",
      "FieldValue": "1"
    },
    {
      "CategoryName": "FFB Blaster",
      "FieldName": "Enable",
      "FieldOptions": [],
      "FieldType": "Bool",
      "FieldValue": "0"
    },
    {
      "CategoryName": "General",
      "FieldName": "Enable Outputs",
      "FieldOptions": [],
      "FieldType": "Bool",
      "FieldValue": "0"
    },
    {
      "CategoryName": "General",
      "FieldName": "FreezeCountdownTimer",
      "FieldOptions": [],
      "FieldType": "Bool",
      "FieldValue": "0"
    },
    {
      "CategoryName": "General",
      "FieldName": "AutoAcclOff",
      "FieldOptions": [],
      "FieldType": "Bool",
      "FieldValue": "0"
    },
    {
      "CategoryName": "General",
      "FieldName": "CustomResolution",
      "FieldOptions": [],
      "FieldType": "Bool",
      "FieldValue": "0"
    },
    {
      "CategoryName": "General",
      "FieldName": "ResolutionWidth",
      "FieldOptions": [],
      "FieldValue": "1360"
    },
    {
      "CategoryName": "General",
      "FieldName": "ResolutionHeight",
      "FieldOptions": [],
      "FieldValue": "768"
    },
    {
      "CategoryName": "General",
      "FieldName": "Use Keyboard/Button For Axis",
      "FieldOptions": [],
      "FieldType": "Bool",
      "FieldValue": "0"
    },
    {
      "CategoryName": "General",
      "FieldMax": 127,
      "FieldMin": 1,
      "FieldName": "Keyboard/Button Axis Wheel Sensitivity",
      "FieldOptions": [],
      "FieldType": "Slider",
      "FieldValue": "10"
    },
    {
      "CategoryName": "General",
      "FieldMax": 255,
      "FieldMin": 1,
      "FieldName": "Keyboard/Button Axis Pedal Sensitivity",
      "FieldOptions": [],
      "FieldType": "Slider",
      "FieldValue": "10"
    },
    {
      "CategoryName": "Network",
      "FieldName": "Gateway",
      "FieldOptions": [],
      "FieldValue": "192.168.1.1"
    }
  ],
  "JoystickButtons": [
    {
      "ButtonName": "Test"
    },
    {
      "ButtonName": "Service",
      "InputMapping": "Service1"
    },
    {
      "ButtonName": "Coin",
      "InputMapping": "Coin1"
    },
    {
      "ButtonName": "Start",
      "InputMapping": "P1ButtonStart"
    },
    {
      "AnalogType": "Wheel",
      "ButtonName": "Wheel Axis",
      "HideWithKeyboardForAxis": true,
      "InputMapping": "Analog0"
    },
    {
      "AnalogType": "Wheel",
      "ButtonName": "Wheel Axis Left",
      "HideWithoutKeyboardForAxis": true,
      "HideWithXInput": true,
      "InputMapping": "Analog0"
    },
    {
      "AnalogType": "Wheel",
      "ButtonName": "Wheel Axis Right",
      "HideWithoutKeyboardForAxis": true,
      "HideWithXInput": true,
      "InputMapping": "Analog0"
    },
    {
      "AnalogType": "Gas",
      "ButtonName": "Gas",
      "InputMapping": "Analog2"
    },
    {
      "ButtonName": "Brake",
      "InputMapping": "P1Button3"
    },
    {
      "ButtonName": "Item",
      "InputMapping": "P1Button5"
    },
    {
      "ButtonName": "Menu Up",
      "InputMapping": "P1ButtonUp"
    },
    {
      "ButtonName": "Menu Down",
      "InputMapping": "P1ButtonDown"
    },
    {
      "ButtonName": "Enter Switch",
      "InputMapping": "P1Button1"
    },
    {
      "ButtonName": "Mario Button",
      "InputMapping": "ExtensionOne2"
    }
  ]
}